telicent_lib/__init__.py
telicent_lib/action.py
telicent_lib/adapter.py
telicent_lib/errors.py
telicent_lib/exceptions.py
telicent_lib/logging.py
telicent_lib/mapper.py
telicent_lib/projector.py
telicent_lib/records.py
telicent_lib/reporter.py
telicent_lib/sbom.json
telicent_lib/status.py
telicent_lib/utils.py
telicent_lib/config/__init__.py
telicent_lib/config/configSource.py
telicent_lib/config/configurator.py
telicent_lib/config/kafka.py
telicent_lib/sinks/__init__.py
telicent_lib/sinks/dataSink.py
telicent_lib/sinks/dictSink.py
telicent_lib/sinks/kafkaSink.py
telicent_lib/sinks/listSink.py
telicent_lib/sinks/serializers.py
telicent_lib/sources/__init__.py
telicent_lib/sources/dataSource.py
telicent_lib/sources/deserializers.py
telicent_lib/sources/dictSource.py
telicent_lib/sources/kafkaSource.py
telicent_lib/sources/listSource.py
telicent_lib-6.1.0.dist-info/licenses/LICENSE
telicent_lib-6.1.0.dist-info/licenses/NOTICE
telicent_lib-6.1.0.dist-info/METADATA
telicent_lib-6.1.0.dist-info/WHEEL
telicent_lib-6.1.0.dist-info/top_level.txt
telicent_lib-6.1.0.dist-info/RECORD
