Metadata-Version: 2.4
Name: telicent-lib
Version: 6.1.0
Summary: A helper package for building Adapters, Mappers and Projectors for Telicent Core
Author-email: Telicent Ltd <opensource@telicent.io>
License:                                  Apache License
Project-URL: Repository, https://github.com/telicent-oss/telicent-lib
Classifier: Programming Language :: Python :: 3.10
Classifier: Programming Language :: Python :: 3.11
Classifier: Programming Language :: Python :: 3.12
Classifier: Programming Language :: Python :: 3.13
Classifier: Programming Language :: Python :: 3 :: Only
Classifier: Topic :: Software Development
Classifier: Typing :: Typed
Classifier: Operating System :: Microsoft :: Windows
Classifier: Operating System :: POSIX
Classifier: Operating System :: Unix
Classifier: Operating System :: MacOS
Requires-Python: >=3.10
License-File: LICENSE
License-File: NOTICE
Requires-Dist: colored==2.3.1
Requires-Dist: pytz==2025.2
Requires-Dist: confluent-kafka==2.8.2
Requires-Dist: opentelemetry-api>=1.20.0
Requires-Dist: opentelemetry-sdk>=1.20.0
Provides-Extra: dev
Requires-Dist: pre-commit==3.5.0; extra == "dev"
Requires-Dist: ruff==0.1.5; extra == "dev"
Requires-Dist: types-pytz==2023.3.1.1; extra == "dev"
Requires-Dist: urllib3==2.2.2; extra == "dev"
Requires-Dist: types-requests==2.32.0.20240622; extra == "dev"
Requires-Dist: mypy==1.7.0; extra == "dev"
Requires-Dist: mkdocs==1.5.3; extra == "dev"
Requires-Dist: cyclonedx-bom==4.4.3; extra == "dev"
Dynamic: license-file
